trens/__init__.py
trens/dados.py
diretodostrens-0.0.2.dist-info/LICENSE
diretodostrens-0.0.2.dist-info/METADATA
diretodostrens-0.0.2.dist-info/WHEEL
diretodostrens-0.0.2.dist-info/top_level.txt
diretodostrens-0.0.2.dist-info/RECORD
